mergesv/__init__.py
mergesv/merge.py
mergesv/mergesv.py
mergesv-1.4.data/scripts/merge.py
mergesv-1.4.data/scripts/mergesv
mergesv-1.4.dist-info/LICENSE
mergesv-1.4.dist-info/METADATA
mergesv-1.4.dist-info/WHEEL
mergesv-1.4.dist-info/top_level.txt
mergesv-1.4.dist-info/RECORD
