Metadata-Version: 2.1
Name: mergesv
Version: 1.4
Summary: Merge overlapping SVs
Home-page: https://github.com/daverbuj/MergeSV
Author: Dan Averbuj
Author-email: dan.averbuj@gmail.com
License: UNKNOWN
Platform: UNKNOWN
Requires: csv
Requires: argparse
Requires: operator
Requires-Python: >=3.6
